setup.py
wsb/__init__.py
wsb/wsb.py
wsb.egg-info/PKG-INFO
wsb.egg-info/SOURCES.txt
wsb.egg-info/dependency_links.txt
wsb.egg-info/top_level.txt